LICENSE.txt
README.md
setup.cfg
setup.py
Topsis_Arnav_102103162/102103162.py
Topsis_Arnav_102103162/__init__.py
Topsis_Arnav_102103162.egg-info/PKG-INFO
Topsis_Arnav_102103162.egg-info/SOURCES.txt
Topsis_Arnav_102103162.egg-info/dependency_links.txt
Topsis_Arnav_102103162.egg-info/requires.txt
Topsis_Arnav_102103162.egg-info/top_level.txt