Metadata-Version: 2.1
Name: Topsis-Arnav-102103162
Version: 0.1
Summary: Contains the Topsis package by Arnav Sharma(102103162)
Home-page: https://github.com/arnavroh45/Topsis_Arnav_102103162
Download-URL: https://github.com/arnavroh45/Topsis_Arnav_102103162/archive/refs/tags/0.1.tar.gz
Author: Arnav Sharma
Author-email: arnavroh45@gmail.com
License: MIT
Keywords: SOME,MEANINGFULL,KEYWORDS
License-File: LICENSE.txt
